{
    "ml_dataset_all_possible_labels": [
        0,
        1,
        2,
        3,
        4,
        5,
        6,
        7,
        8,
        9
    ],
    "ml_delayed_test_accuracy": false,
    "ml_max_tick": 4000,
    "ml_non_iid_normal_weight": [
        10.0,
        15.0
    ],
    "ml_reputation_dll_path": "../libreputation_HalfFedAvg.so",
    "ml_solver_proto": "../dataset/MNIST/lenet_solver_memory.prototxt",
    "ml_test_batch_size": 100,
    "ml_test_dataset": "../dataset/MNIST/t10k-images.idx3-ubyte",
    "ml_test_dataset_label": "../dataset/MNIST/t10k-labels.idx1-ubyte",
    "ml_train_batch_size": 64,
    "ml_train_dataset": "../dataset/MNIST/train-images.idx3-ubyte",
    "ml_train_dataset_label": "../dataset/MNIST/train-labels.idx1-ubyte",
    "node_topology": [
        "0--3",
        "0--8",
        "1--5",
        "1--7",
        "2--0",
        "2--8",
        "3--4",
        "3--7",
        "4--8",
        "4--9",
        "5--3",
        "5--4",
        "6--5",
        "6--4",
        "7--6",
        "7--5",
        "8--1",
        "8--2",
        "9--5",
        "9--1"
    ],
    "nodes": [
        {
            "buffer_size": 4,
            "dataset_mode": "non-iid",
            "filter_limit": 0.5,
            "model_generation_type": "normal",
            "name": "0",
            "node_type": "normal",
            "non_iid_distribution": {
                "0": [
                    654.3171997070313,
                    654.3171997070313
                ],
                "1": [
                    350.97369384765625,
                    350.97369384765625
                ],
                "2": [
                    1472.49853515625,
                    1472.49853515625
                ],
                "3": [
                    5.159257199238709e-08,
                    5.159257199238709e-08
                ],
                "4": [
                    6297.0234375,
                    6297.0234375
                ],
                "5": [
                    112296.7109375,
                    112296.7109375
                ],
                "6": [
                    5.2706455570873265e-18,
                    5.2706455570873265e-18
                ],
                "7": [
                    5.121582984924316,
                    5.121582984924316
                ],
                "8": [
                    0.004728573374450207,
                    0.004728573374450207
                ],
                "9": [
                    4342.68994140625,
                    4342.68994140625
                ]
            },
            "training_interval_tick": [
                8,
                9,
                10,
                11,
                12
            ]
        },
        {
            "buffer_size": 4,
            "dataset_mode": "non-iid",
            "filter_limit": 0.5,
            "model_generation_type": "normal",
            "name": "1",
            "node_type": "normal",
            "non_iid_distribution": {
                "0": [
                    0.008198915980756283,
                    0.008198915980756283
                ],
                "1": [
                    1009.6813354492188,
                    1009.6813354492188
                ],
                "2": [
                    0.010644243098795414,
                    0.010644243098795414
                ],
                "3": [
                    3216.83984375,
                    3216.83984375
                ],
                "4": [
                    545.3095092773438,
                    545.3095092773438
                ],
                "5": [
                    2.2160038497531787e-05,
                    2.2160038497531787e-05
                ],
                "6": [
                    3455.759521484375,
                    3455.759521484375
                ],
                "7": [
                    42614.0859375,
                    42614.0859375
                ],
                "8": [
                    140.77635192871094,
                    140.77635192871094
                ],
                "9": [
                    62636.90625,
                    62636.90625
                ]
            },
            "training_interval_tick": [
                8,
                9,
                10,
                11,
                12
            ]
        },
        {
            "buffer_size": 4,
            "dataset_mode": "non-iid",
            "filter_limit": 0.5,
            "model_generation_type": "normal",
            "name": "2",
            "node_type": "normal",
            "non_iid_distribution": {
                "0": [
                    108.23176574707031,
                    108.23176574707031
                ],
                "1": [
                    0.4629935622215271,
                    0.4629935622215271
                ],
                "2": [
                    1.6356562376022339,
                    1.6356562376022339
                ],
                "3": [
                    54669.91796875,
                    54669.91796875
                ],
                "4": [
                    19478.748046875,
                    19478.748046875
                ],
                "5": [
                    6.747116003680276e-07,
                    6.747116003680276e-07
                ],
                "6": [
                    0.12369053810834885,
                    0.12369053810834885
                ],
                "7": [
                    21184.95703125,
                    21184.95703125
                ],
                "8": [
                    0.004968486726284027,
                    0.004968486726284027
                ],
                "9": [
                    28168.783203125,
                    28168.783203125
                ]
            },
            "training_interval_tick": [
                8,
                9,
                10,
                11,
                12
            ]
        },
        {
            "buffer_size": 4,
            "dataset_mode": "non-iid",
            "filter_limit": 0.5,
            "model_generation_type": "normal",
            "name": "3",
            "node_type": "normal",
            "non_iid_distribution": {
                "0": [
                    7.2910966873168945,
                    7.2910966873168945
                ],
                "1": [
                    3013.87548828125,
                    3013.87548828125
                ],
                "2": [
                    0.00171302177477628,
                    0.00171302177477628
                ],
                "3": [
                    1100.8173828125,
                    1100.8173828125
                ],
                "4": [
                    57.133758544921875,
                    57.133758544921875
                ],
                "5": [
                    0.02942120097577572,
                    0.02942120097577572
                ],
                "6": [
                    2637.2197265625,
                    2637.2197265625
                ],
                "7": [
                    458.1229248046875,
                    458.1229248046875
                ],
                "8": [
                    132213.40625,
                    132213.40625
                ],
                "9": [
                    6717.1298828125,
                    6717.1298828125
                ]
            },
            "training_interval_tick": [
                8,
                9,
                10,
                11,
                12
            ]
        },
        {
            "buffer_size": 4,
            "dataset_mode": "non-iid",
            "filter_limit": 0.5,
            "model_generation_type": "normal",
            "name": "4",
            "node_type": "normal",
            "non_iid_distribution": {
                "0": [
                    108.66242218017578,
                    108.66242218017578
                ],
                "1": [
                    6599.88671875,
                    6599.88671875
                ],
                "2": [
                    0.17185631394386292,
                    0.17185631394386292
                ],
                "3": [
                    32136.9375,
                    32136.9375
                ],
                "4": [
                    4486.3662109375,
                    4486.3662109375
                ],
                "5": [
                    1746.1768798828125,
                    1746.1768798828125
                ],
                "6": [
                    62.96626663208008,
                    62.96626663208008
                ],
                "7": [
                    0.0043611833825707436,
                    0.0043611833825707436
                ],
                "8": [
                    0.01697694882750511,
                    0.01697694882750511
                ],
                "9": [
                    91.53572845458984,
                    91.53572845458984
                ]
            },
            "training_interval_tick": [
                8,
                9,
                10,
                11,
                12
            ]
        },
        {
            "buffer_size": 4,
            "dataset_mode": "non-iid",
            "filter_limit": 0.5,
            "model_generation_type": "normal",
            "name": "5",
            "node_type": "normal",
            "non_iid_distribution": {
                "0": [
                    1.5387760727891471e-18,
                    1.5387760727891471e-18
                ],
                "1": [
                    301.21417236328125,
                    301.21417236328125
                ],
                "2": [
                    1803.1439208984375,
                    1803.1439208984375
                ],
                "3": [
                    9815.9228515625,
                    9815.9228515625
                ],
                "4": [
                    4.802192211151123,
                    4.802192211151123
                ],
                "5": [
                    0.0007908089901320636,
                    0.0007908089901320636
                ],
                "6": [
                    32170.357421875,
                    32170.357421875
                ],
                "7": [
                    1.1397828529879916e-05,
                    1.1397828529879916e-05
                ],
                "8": [
                    0.885440468788147,
                    0.885440468788147
                ],
                "9": [
                    0.11147915571928024,
                    0.11147915571928024
                ]
            },
            "training_interval_tick": [
                8,
                9,
                10,
                11,
                12
            ]
        },
        {
            "buffer_size": 4,
            "dataset_mode": "non-iid",
            "filter_limit": 0.5,
            "model_generation_type": "normal",
            "name": "6",
            "node_type": "normal",
            "non_iid_distribution": {
                "0": [
                    715.9143676757813,
                    715.9143676757813
                ],
                "1": [
                    0.25292253494262695,
                    0.25292253494262695
                ],
                "2": [
                    0.0010178254451602697,
                    0.0010178254451602697
                ],
                "3": [
                    0.0022478809114545584,
                    0.0022478809114545584
                ],
                "4": [
                    0.017059871926903725,
                    0.017059871926903725
                ],
                "5": [
                    0.01854272373020649,
                    0.01854272373020649
                ],
                "6": [
                    33.08047866821289,
                    33.08047866821289
                ],
                "7": [
                    723.1597290039063,
                    723.1597290039063
                ],
                "8": [
                    3915.562744140625,
                    3915.562744140625
                ],
                "9": [
                    8.802903067942069e-13,
                    8.802903067942069e-13
                ]
            },
            "training_interval_tick": [
                8,
                9,
                10,
                11,
                12
            ]
        },
        {
            "buffer_size": 4,
            "dataset_mode": "non-iid",
            "filter_limit": 0.5,
            "model_generation_type": "normal",
            "name": "7",
            "node_type": "normal",
            "non_iid_distribution": {
                "0": [
                    0.0008832713356241584,
                    0.0008832713356241584
                ],
                "1": [
                    551.2086181640625,
                    551.2086181640625
                ],
                "2": [
                    5461.69775390625,
                    5461.69775390625
                ],
                "3": [
                    0.026861580088734627,
                    0.026861580088734627
                ],
                "4": [
                    6418.2275390625,
                    6418.2275390625
                ],
                "5": [
                    107.33715057373047,
                    107.33715057373047
                ],
                "6": [
                    65915.7578125,
                    65915.7578125
                ],
                "7": [
                    0.039568424224853516,
                    0.039568424224853516
                ],
                "8": [
                    3804.931884765625,
                    3804.931884765625
                ],
                "9": [
                    0.01651940308511257,
                    0.01651940308511257
                ]
            },
            "training_interval_tick": [
                8,
                9,
                10,
                11,
                12
            ]
        },
        {
            "buffer_size": 4,
            "dataset_mode": "non-iid",
            "filter_limit": 0.5,
            "model_generation_type": "normal",
            "name": "8",
            "node_type": "normal",
            "non_iid_distribution": {
                "0": [
                    2114.548583984375,
                    2114.548583984375
                ],
                "1": [
                    1.8118382286047563e-05,
                    1.8118382286047563e-05
                ],
                "2": [
                    11505.583984375,
                    11505.583984375
                ],
                "3": [
                    2.000039239646867e-05,
                    2.000039239646867e-05
                ],
                "4": [
                    0.11962378025054932,
                    0.11962378025054932
                ],
                "5": [
                    0.0003069349913857877,
                    0.0003069349913857877
                ],
                "6": [
                    49.65863037109375,
                    49.65863037109375
                ],
                "7": [
                    0.008853171020746231,
                    0.008853171020746231
                ],
                "8": [
                    23420.96875,
                    23420.96875
                ],
                "9": [
                    1.068710207939148,
                    1.068710207939148
                ]
            },
            "training_interval_tick": [
                8,
                9,
                10,
                11,
                12
            ]
        },
        {
            "buffer_size": 4,
            "dataset_mode": "non-iid",
            "filter_limit": 0.5,
            "model_generation_type": "normal",
            "name": "9",
            "node_type": "normal",
            "non_iid_distribution": {
                "0": [
                    103.3113784790039,
                    103.3113784790039
                ],
                "1": [
                    1.0248663784295786e-05,
                    1.0248663784295786e-05
                ],
                "2": [
                    18889.60546875,
                    18889.60546875
                ],
                "3": [
                    4.768948347333435e-09,
                    4.768948347333435e-09
                ],
                "4": [
                    0.004972395952790976,
                    0.004972395952790976
                ],
                "5": [
                    0.0004855944134760648,
                    0.0004855944134760648
                ],
                "6": [
                    0.10391218960285187,
                    0.10391218960285187
                ],
                "7": [
                    723.9998168945313,
                    723.9998168945313
                ],
                "8": [
                    83.35814666748047,
                    83.35814666748047
                ],
                "9": [
                    28.222881317138672,
                    28.222881317138672
                ]
            },
            "training_interval_tick": [
                8,
                9,
                10,
                11,
                12
            ]
        }
    ],
    "report_time_remaining_per_tick_elapsed": 100,
    "services": {
        "accuracy": {
            "enable": true,
            "interval": 20
        },
        "force_broadcast_average": {
            "broadcast_interval": 100,
            "enable": false
        },
        "peer_control_service": {
            "accuracy_threshold_high": 0.8,
            "accuracy_threshold_low": 0.2,
            "enable": false,
            "fedavg_buffer_size": "linear",
            "least_peer_change_interval": 50
        },
        "weights_diff": {
            "enable": true,
            "interval": 20
        }
    }
}